{
  "XML_Head": {
    "Listname": "1",
    "Language": "C",
    "Orgname": "315080000H",
    "Updatetime": "2021-01-06T01:11:20+08:00",
    "Infos": {
      "Info": [
        {
          "Id": "C1_313020000G_000026",
          "Name": "宏亞食品巧克力觀光工廠",
          "Region": "桃園市",
          "Town": "八德區"
        },
        {
          "Id": "C1_313020000G_000105",
          "Name": "台灣金屬創意館",
          "Region": "臺南市",
          "Town": "永康區"
        },
        {
          "Id": "C1_313020000G_000136",
          "Name": "臺灣菸酒(股)公司林口觀光酒廠",
          "Region": "桃園市",
          "Town": "龜山區"
        },
        {
          "Id": "C1_315080500H_000007",
          "Name": "水璉、牛山海岸",
          "Region": "花蓮縣",
          "Town": "壽豐鄉"
        },
        {
          "Id": "C1_315080500H_000012",
          "Name": "石梯坪",
          "Region": "花蓮縣",
          "Town": "豐濱鄉"
        },
        {
          "Id": "C1_315080500H_000014",
          "Name": "長虹橋",
          "Region": "花蓮縣",
          "Town": "豐濱鄉"
        },
        {
          "Id": "C1_315080500H_000015",
          "Name": "北回歸線",
          "Region": "花蓮縣",
          "Town": "豐濱鄉"
        }
      ]
    }
  }
}
